nedry_pass/Nedry_01.gif
nedry_pass/Nedry_02.gif
nedry_pass/Nedry_03.gif
nedry_pass/Nedry_04.gif
nedry_pass/Nedry_05.gif
nedry_pass/__init__.py
nedry_pass/__init__.pyc
nedry_pass/_main.py
nedry_pass/_main.pyc
nedry_pass/front.JPG
nedry_pass/magic_word.wav
nedry_pass/runTest.bat
nedry_pass-0.0.6.dist-info/DESCRIPTION.rst
nedry_pass-0.0.6.dist-info/METADATA
nedry_pass-0.0.6.dist-info/RECORD
nedry_pass-0.0.6.dist-info/WHEEL
nedry_pass-0.0.6.dist-info/entry_points.txt
nedry_pass-0.0.6.dist-info/metadata.json
nedry_pass-0.0.6.dist-info/top_level.txt
