Metadata-Version: 2.0
Name: nedry-pass
Version: 0.0.6
Summary: A security package for those tough jobs.
Home-page: https://github.com/Duroktar/nedry_pass
Author: Scott Doucet
Author-email: duroktar@gmail.com
License: BSD
Download-URL: https://github.com/Duroktar/nedry_pass/tarball/0.0.6
Platform: UNKNOWN
Classifier: Development Status :: 3 - Alpha
Classifier: Intended Audience :: Developers
Classifier: Programming Language :: Python :: 2.7
